{
  "formatVersion": 1,
  "database": {
    "version": 1,
    "identityHash": "d62a10c655a2864e41e60256d93d966f",
    "entities": [
      {
        "tableName": "projeto",
        "createSql": "CREATE TABLE IF NOT EXISTS `${TABLE_NAME}` (`id` INTEGER NOT NULL, `nome` TEXT NOT NULL, `inicio` INTEGER NOT NULL, `estimativa_conclusao` INTEGER NOT NULL, PRIMARY KEY(`id`))",
        "fields": [
          {
            "fieldPath": "id",
            "columnName": "id",
            "affinity": "INTEGER",
            "notNull": true
          },
          {
            "fieldPath": "nome",
            "columnName": "nome",
            "affinity": "TEXT",
            "notNull": true
          },
          {
            "fieldPath": "inicio",
            "columnName": "inicio",
            "affinity": "INTEGER",
            "notNull": true
          },
          {
            "fieldPath": "estimativaConclusao",
            "columnName": "estimativa_conclusao",
            "affinity": "INTEGER",
            "notNull": true
          }
        ],
        "primaryKey": {
          "columnNames": [
            "id"
          ],
          "autoGenerate": false
        },
        "indices": [],
        "foreignKeys": []
      },
      {
        "tableName": "requisito",
        "createSql": "CREATE TABLE IF NOT EXISTS `${TABLE_NAME}` (`id_projeto` INTEGER NOT NULL, `id` INTEGER NOT NULL, `descricao` TEXT NOT NULL, `criacao` INTEGER NOT NULL, `importancia` INTEGER NOT NULL, `dificuldade` INTEGER NOT NULL, `horas_para_conclucao` INTEGER NOT NULL, PRIMARY KEY(`id_projeto`, `id`), FOREIGN KEY(`id_projeto`) REFERENCES `projeto`(`id`) ON UPDATE NO ACTION ON DELETE NO ACTION )",
        "fields": [
          {
            "fieldPath": "idProjeto",
            "columnName": "id_projeto",
            "affinity": "INTEGER",
            "notNull": true
          },
          {
            "fieldPath": "id",
            "columnName": "id",
            "affinity": "INTEGER",
            "notNull": true
          },
          {
            "fieldPath": "descricao",
            "columnName": "descricao",
            "affinity": "TEXT",
            "notNull": true
          },
          {
            "fieldPath": "criacao",
            "columnName": "criacao",
            "affinity": "INTEGER",
            "notNull": true
          },
          {
            "fieldPath": "importancia",
            "columnName": "importancia",
            "affinity": "INTEGER",
            "notNull": true
          },
          {
            "fieldPath": "dificuldade",
            "columnName": "dificuldade",
            "affinity": "INTEGER",
            "notNull": true
          },
          {
            "fieldPath": "horasParaConclucao",
            "columnName": "horas_para_conclucao",
            "affinity": "INTEGER",
            "notNull": true
          }
        ],
        "primaryKey": {
          "columnNames": [
            "id_projeto",
            "id"
          ],
          "autoGenerate": false
        },
        "indices": [],
        "foreignKeys": [
          {
            "table": "projeto",
            "onDelete": "NO ACTION",
            "onUpdate": "NO ACTION",
            "columns": [
              "id_projeto"
            ],
            "referencedColumns": [
              "id"
            ]
          }
        ]
      }
    ],
    "views": [],
    "setupQueries": [
      "CREATE TABLE IF NOT EXISTS room_master_table (id INTEGER PRIMARY KEY,identity_hash TEXT)",
      "INSERT OR REPLACE INTO room_master_table (id,identity_hash) VALUES(42, 'd62a10c655a2864e41e60256d93d966f')"
    ]
  }
}